pyspark/__init__.py
pyspark/__init__.pyi
pyspark/_globals.py
pyspark/_typing.pyi
pyspark/accumulators.py
pyspark/accumulators.pyi
pyspark/broadcast.py
pyspark/broadcast.pyi
pyspark/conf.py
pyspark/conf.pyi
pyspark/context.py
pyspark/context.pyi
pyspark/daemon.py
pyspark/files.py
pyspark/files.pyi
pyspark/find_spark_home.py
pyspark/install.py
pyspark/java_gateway.py
pyspark/join.py
pyspark/profiler.py
pyspark/profiler.pyi
pyspark/py.typed
pyspark/rdd.py
pyspark/rdd.pyi
pyspark/rddsampler.py
pyspark/resultiterable.py
pyspark/resultiterable.pyi
pyspark/serializers.py
pyspark/shell.py
pyspark/shuffle.py
pyspark/statcounter.py
pyspark/statcounter.pyi
pyspark/status.py
pyspark/status.pyi
pyspark/storagelevel.py
pyspark/storagelevel.pyi
pyspark/taskcontext.py
pyspark/taskcontext.pyi
pyspark/traceback_utils.py
pyspark/util.py
pyspark/util.pyi
pyspark/version.py
pyspark/version.pyi
pyspark/worker.py
pyspark/bin/beeline
pyspark/bin/beeline.cmd
pyspark/bin/docker-image-tool.sh
pyspark/bin/find-spark-home
pyspark/bin/find-spark-home.cmd
pyspark/bin/load-spark-env.cmd
pyspark/bin/load-spark-env.sh
pyspark/bin/pyspark
pyspark/bin/pyspark.cmd
pyspark/bin/pyspark2.cmd
pyspark/bin/run-example
pyspark/bin/run-example.cmd
pyspark/bin/spark-class
pyspark/bin/spark-class.cmd
pyspark/bin/spark-class2.cmd
pyspark/bin/spark-shell
pyspark/bin/spark-shell.cmd
pyspark/bin/spark-shell2.cmd
pyspark/bin/spark-sql
pyspark/bin/spark-sql.cmd
pyspark/bin/spark-sql2.cmd
pyspark/bin/spark-submit
pyspark/bin/spark-submit.cmd
pyspark/bin/spark-submit2.cmd
pyspark/bin/sparkR
pyspark/bin/sparkR.cmd
pyspark/bin/sparkR2.cmd
pyspark/cloudpickle/__init__.py
pyspark/cloudpickle/cloudpickle.py
pyspark/cloudpickle/cloudpickle_fast.py
pyspark/cloudpickle/compat.py
pyspark/conf/fairscheduler.xml.template
pyspark/conf/log4j.properties.template
pyspark/conf/metrics.properties.template
pyspark/conf/spark-defaults.conf.template
pyspark/conf/spark-env.sh.template
pyspark/conf/workers.template
ytsaurus_pyspark-1.78.0.dist-info/METADATA
ytsaurus_pyspark-1.78.0.dist-info/WHEEL
ytsaurus_pyspark-1.78.0.dist-info/top_level.txt
ytsaurus_pyspark-1.78.0.dist-info/RECORD
