Metadata-Version: 2.1
Name: ytsaurus-pyspark
Version: 1.78.0
Summary: Apache Spark Python API, YTsaurus fork
Home-page: https://github.com/ytsaurus/ytsaurus/tree/main/yt/spark/spark/python
Author: Spark Developers
Author-email: dev@spark.apache.org
License: http://www.apache.org/licenses/LICENSE-2.0
Classifier: Development Status :: 5 - Production/Stable
Classifier: License :: OSI Approved :: Apache Software License
Classifier: Programming Language :: Python :: 3.6
Classifier: Programming Language :: Python :: 3.7
Classifier: Programming Language :: Python :: 3.8
Classifier: Programming Language :: Python :: 3.9
Classifier: Programming Language :: Python :: Implementation :: CPython
Classifier: Programming Language :: Python :: Implementation :: PyPy
Classifier: Typing :: Typed
Requires-Python: >=3.6
Requires-Dist: py4j ==0.10.9.5
Provides-Extra: ml
Requires-Dist: numpy >=1.7 ; extra == 'ml'
Provides-Extra: mllib
Requires-Dist: numpy >=1.7 ; extra == 'mllib'
Provides-Extra: pandas_on_spark
Requires-Dist: pandas >=0.23.2 ; extra == 'pandas_on_spark'
Requires-Dist: pyarrow >=1.0.0 ; extra == 'pandas_on_spark'
Requires-Dist: numpy >=1.14 ; extra == 'pandas_on_spark'
Provides-Extra: sql
Requires-Dist: pandas >=0.23.2 ; extra == 'sql'
Requires-Dist: pyarrow >=1.0.0 ; extra == 'sql'
